README.md
setup.py
django_rtk_magic_link/__init__.py
django_rtk_magic_link/admin.py
django_rtk_magic_link/apps.py
django_rtk_magic_link/backends.py
django_rtk_magic_link/models.py
django_rtk_magic_link/validators.py
django_rtk_magic_link.egg-info/PKG-INFO
django_rtk_magic_link.egg-info/SOURCES.txt
django_rtk_magic_link.egg-info/dependency_links.txt
django_rtk_magic_link.egg-info/not-zip-safe
django_rtk_magic_link.egg-info/requires.txt
django_rtk_magic_link.egg-info/top_level.txt
django_rtk_magic_link/migrations/0001_initial.py
django_rtk_magic_link/migrations/__init__.py
django_rtk_magic_link/mutations/__init__.py
django_rtk_magic_link/mutations/requestmagiclink.py
django_rtk_magic_link/mutations/signinbymagiclink.py
django_rtk_magic_link/queries/__init__.py