Metadata-Version: 2.1
Name: django-rtk-magic-link
Version: 0.6.0
Summary: Extension of django-rtk that implements the magic-link endpoints
Home-page: https://github.com/mnieber/django-rtk-home/blob/main/django-rtk-magic-link/README.md
Author: Maarten Nieber
Author-email: hallomaarten@yahoo.com
License: MIT
Platform: UNKNOWN
Requires-Python: >=3.6
